{
    "entries": [
        {
            "name": "Artbook",
            "short": " | demonstrative portfolio",
            "description": "A collection of pieces I have done over the years, for personal, professional, or educational purposes.",
            "tags": "",
            "source": "artbook.html"
        },
        {
            "name": "Github",
            "short": " | development projects",
            "description": "Not many projects have been migrated here, more will come in the future.",
            "tags": "",
            "source": "https://github.com/NottMatt"
        },
        {
            "name": "Music",
            "short": " | experimental tracks",
            "description": "Every once in a while, inspiration strikes. Here are some music memes.",
            "tags": "",
            "source": "music.html"
        }
    ]
}